{"cameraMode":{"drawMode":0,"name":"Shaded","section":"Shading Mode"},"sceneLighting":true,"audioPlay":false,"sceneViewState":{"m_AlwaysRefresh":false,"showFog":true,"showSkybox":true,"showFlares":true,"showImageEffects":true,"showParticleSystems":true,"showVisualEffectGraphs":true,"m_FxEnabled":true},"in2DMode":false,"pivot":{"x":-58.2793083190918,"y":129.4069061279297,"z":-1.2279545068740845},"rotation":{"x":-0.07850275933742523,"y":-0.9211040735244751,"z":-0.23030050098896027,"w":0.30503004789352419},"size":0.1272042989730835,"orthographic":false}